{"DE":{"name":"Germany","regions":{"DE_Ansbach":{"name":"Ansbach"},"DE_Arnsberg":{"name":"Arnsberg"},"DE_Augsburg":{"name":"Augsburg"},"DE_Bayreuth":{"name":"Bayreuth"},"DE_Berlin":{"name":"Berlin"},"DE_Bielefeld":{"name":"Bielefeld"},"DE_Bochum":{"name":"Bochum"},"DE_Bremen":{"name":"Bremen"},"DE_Brunswick":{"name":"Brunswick"},"DE_Chemnitz":{"name":"Chemnitz"},"DE_Cologne":{"name":"Cologne"},"DE_Darmstadt":{"name":"Darmstadt"},"DE_Dessau":{"name":"Dessau"},"DE_Detmold":{"name":"Detmold"},"DE_Dresden":{"name":"Dresden"},"DE_Dusseldorf":{"name":"Dusseldorf"},"DE_Erfurt":{"name":"Erfurt"},"DE_Frankfurt":{"name":"Frankfurt"},"DE_Freiburg":{"name":"Freiburg"},"DE_GieBen":{"name":"GieBen"},"DE_Halle":{"name":"Halle"},"DE_Hamburg":{"name":"Hamburg"},"DE_Hannover":{"name":"Hannover"},"DE_Karlsruhe":{"name":"Karlsruhe"},"DE_Kassel":{"name":"Kassel"},"DE_Kiel":{"name":"Kiel"},"DE_Koblenz":{"name":"Koblenz"},"DE_Landshut":{"name":"Landshut"},"DE_Leipzig":{"name":"Leipzig"},"DE_Luneburg":{"name":"Luneburg"},"DE_Magdeburg":{"name":"Magdeburg"},"DE_Mainz":{"name":"Mainz"},"DE_Mannheim":{"name":"Mannheim"},"DE_Muenster":{"name":"Muenster"},"DE_Munich":{"name":"Munich"},"DE_Nuremberg":{"name":"Nuremberg"},"DE_Potsdam":{"name":"Potsdam"},"DE_Schwerin":{"name":"Schwerin"},"DE_Stuttgart":{"name":"Stuttgart"},"DE_Trier":{"name":"Trier"},"DE_Wiesbaden":{"name":"Wiesbaden"},"DE_Wuerzburg":{"name":"Wuerzburg"}}},"MO":{"name":"Macau","regions":{"MO_Cathedral":{"name":"Cathedral"},"MO_Coloane":{"name":"Coloane"},"MO_Fatima":{"name":"Fatima"},"MO_St. Anthony":{"name":"St. Anthony"},"MO_St. Lawrence":{"name":"St. Lawrence"},"MO_St. Lazarus":{"name":"St. Lazarus"},"MO_Taipa":{"name":"Taipa"}}},"TW":{"name":"Taiwan","regions":{"TW_New Taipei":{"name":"New Taipei"},"TW_Kaohsiung":{"name":"Kaohsiung"},"TW_Taichung":{"name":"Taichung"},"TW_Taipei":{"name":"Taipei"},"TW_Tainan":{"name":"Tainan"},"TW_Hsinchu":{"name":"Hsinchu"},"TW_Taoyuan":{"name":"Taoyuan"},"TW_Keelung":{"name":"Keelung"},"TW_Zhongli":{"name":"Zhongli"},"TW_Chiayi":{"name":"Chiayi"},"TW_Changhua":{"name":"Changhua"},"TW_Pingzhen":{"name":"Pingzhen"},"TW_Pingtung":{"name":"Pingtung"},"TW_Bade":{"name":"Bade"},"TW_Yangmei":{"name":"Yangmei"},"TW_Zhubei":{"name":"Zhubei"},"TW_Hualien":{"name":"Hualien"},"TW_Douliu":{"name":"Douliu"},"TW_Taitung":{"name":"Taitung"},"TW_Nantou":{"name":"Nantou"},"TW_Yilan":{"name":"Yilan"},"TW_Miaoli":{"name":"Miaoli"},"TW_Magong":{"name":"Magong"},"TW_Puzi":{"name":"Puzi"},"TW_Taibao":{"name":"Taibao"}}},"HK":{"name":"Hong Kong","regions":{"HK_New Territories":{"name":"New Territories"},"HK_Kowloon":{"name":"Kowloon"},"HK_Hong Kong Island":{"name":"Hong Kong Island"}}},"JP":{"name":"Japan","regions":{"JP_Aichi":{"name":"Aichi"},"JP_Akita":{"name":"Akita"},"JP_Aomori":{"name":"Aomori"},"JP_Chiba":{"name":"Chiba"},"JP_Ehime":{"name":"Ehime"},"JP_Fukui":{"name":"Fukui"},"JP_Fukuoka":{"name":"Fukuoka"},"JP_Fukushima":{"name":"Fukushima"},"JP_Gifu":{"name":"Gifu"},"JP_Gunma":{"name":"Gunma"},"JP_Hiroshima":{"name":"Hiroshima"},"JP_Hokkaido":{"name":"Hokkaido"},"JP_Hyogo":{"name":"Hyogo"},"JP_Ibaraki":{"name":"Ibaraki"},"JP_Ishikawa":{"name":"Ishikawa"},"JP_Iwate":{"name":"Iwate"},"JP_Kagawa":{"name":"Kagawa"},"JP_Kagoshima":{"name":"Kagoshima"},"JP_Kanagawa":{"name":"Kanagawa"},"JP_Kochi":{"name":"Kochi"},"JP_Kumamoto":{"name":"Kumamoto"},"JP_Kyoto":{"name":"Kyoto"},"JP_Mie":{"name":"Mie"},"JP_Miyagi":{"name":"Miyagi"},"JP_Miyazaki":{"name":"Miyazaki"},"JP_Nagano":{"name":"Nagano"},"JP_Nagasaki":{"name":"Nagasaki"},"JP_Nara":{"name":"Nara"},"JP_Niigata":{"name":"Niigata"},"JP_Oita":{"name":"Oita"},"JP_Okayama":{"name":"Okayama"},"JP_Okinawa":{"name":"Okinawa"},"JP_Osaka":{"name":"Osaka"},"JP_Saga":{"name":"Saga"},"JP_Saitama":{"name":"Saitama"},"JP_Shiga":{"name":"Shiga"},"JP_Shimane":{"name":"Shimane"},"JP_Shizuoka":{"name":"Shizuoka"},"JP_Tochigi":{"name":"Tochigi"},"JP_Tokushima":{"name":"Tokushima"},"JP_Tokyo":{"name":"Tokyo"},"JP_Tottori":{"name":"Tottori"},"JP_Toyama":{"name":"Toyama"},"JP_Wakayama":{"name":"Wakayama"},"JP_Yamagata":{"name":"Yamagata"},"JP_Yamaguchi":{"name":"Yamaguchi"},"JP_Yamanashi":{"name":"Yamanashi"}}},"KR":{"name":"Korea","regions":{"KR_Busan":{"name":"Busan"},"KR_Chungcheongbuk-do":{"name":"Chungcheongbuk-do","regions":{"KR_Chungcheongbuk-do_Andong":{"name":"Andong"},"KR_Chungcheongbuk-do_Bonghwa County":{"name":"Bonghwa County"},"KR_Chungcheongbuk-do_Cheongdo County":{"name":"Cheongdo County"},"KR_Chungcheongbuk-do_Cheongsong County":{"name":"Cheongsong County"},"KR_Chungcheongbuk-do_Chilgok County":{"name":"Chilgok County"},"KR_Chungcheongbuk-do_Gimcheon":{"name":"Gimcheon"},"KR_Chungcheongbuk-do_Goryeong County":{"name":"Goryeong County"},"KR_Chungcheongbuk-do_Gumi":{"name":"Gumi"},"KR_Chungcheongbuk-do_Gunwi County":{"name":"Gunwi County"},"KR_Chungcheongbuk-do_Gyeongju":{"name":"Gyeongju"},"KR_Chungcheongbuk-do_Gyeongsan":{"name":"Gyeongsan"},"KR_Chungcheongbuk-do_Mungyeong":{"name":"Mungyeong"},"KR_Chungcheongbuk-do_Pohang":{"name":"Pohang"},"KR_Chungcheongbuk-do_Sangju":{"name":"Sangju"},"KR_Chungcheongbuk-do_Seongju County":{"name":"Seongju County"},"KR_Chungcheongbuk-do_Uiseong County":{"name":"Uiseong County"},"KR_Chungcheongbuk-do_Uljin County":{"name":"Uljin County"},"KR_Chungcheongbuk-do_Ulleung County":{"name":"Ulleung County"},"KR_Chungcheongbuk-do_Yecheon County":{"name":"Yecheon County"},"KR_Chungcheongbuk-do_Yeongcheon":{"name":"Yeongcheon"},"KR_Chungcheongbuk-do_Yeongdeok County":{"name":"Yeongdeok County"},"KR_Chungcheongbuk-do_Yeongju":{"name":"Yeongju"},"KR_Chungcheongbuk-do_Yeongyang County":{"name":"Yeongyang County"}}},"KR_Chungcheongnam-do":{"name":"Chungcheongnam-do","regions":{"KR_Chungcheongnam-do_Changnyeong County":{"name":"Changnyeong County"},"KR_Chungcheongnam-do_Changwon":{"name":"Changwon"},"KR_Chungcheongnam-do_Geochang County":{"name":"Geochang County"},"KR_Chungcheongnam-do_Geoje":{"name":"Geoje"},"KR_Chungcheongnam-do_Gimhae":{"name":"Gimhae"},"KR_Chungcheongnam-do_Goseong County":{"name":"Goseong County"},"KR_Chungcheongnam-do_Hadong County":{"name":"Hadong County"},"KR_Chungcheongnam-do_Haman County":{"name":"Haman County"},"KR_Chungcheongnam-do_Hamyang County":{"name":"Hamyang County"},"KR_Chungcheongnam-do_Hapcheon County":{"name":"Hapcheon County"},"KR_Chungcheongnam-do_Jinhae":{"name":"Jinhae"},"KR_Chungcheongnam-do_Jinju":{"name":"Jinju"},"KR_Chungcheongnam-do_Masan":{"name":"Masan"},"KR_Chungcheongnam-do_Miryang":{"name":"Miryang"},"KR_Chungcheongnam-do_Namhae County":{"name":"Namhae County"},"KR_Chungcheongnam-do_Sacheon":{"name":"Sacheon"},"KR_Chungcheongnam-do_Sancheong County":{"name":"Sancheong County"},"KR_Chungcheongnam-do_Tongyeong":{"name":"Tongyeong"},"KR_Chungcheongnam-do_Uiryeong County":{"name":"Uiryeong County"},"KR_Chungcheongnam-do_Yangsan":{"name":"Yangsan"}}},"KR_Daegu":{"name":"Daegu","regions":{"KR_Daegu_Daegu":{"name":"Daegu"},"KR_Daegu_Dalseong-gun":{"name":"Dalseong-gun"},"KR_Daegu_Suseong-gu":{"name":"Suseong-gu"}}},"KR_Daejeon":{"name":"Daejeon"},"KR_Gangwon-do":{"name":"Gangwon-do","regions":{"KR_Gangwon-do_Cheorwon County":{"name":"Cheorwon County"},"KR_Gangwon-do_Chuncheon":{"name":"Chuncheon"},"KR_Gangwon-do_Donghae":{"name":"Donghae"},"KR_Gangwon-do_Gangneung":{"name":"Gangneung"},"KR_Gangwon-do_Goseong County":{"name":"Goseong County"},"KR_Gangwon-do_Hoengseong County":{"name":"Hoengseong County"},"KR_Gangwon-do_Hongcheon County":{"name":"Hongcheon County"},"KR_Gangwon-do_Hwacheon County":{"name":"Hwacheon County"},"KR_Gangwon-do_Inje County":{"name":"Inje County"},"KR_Gangwon-do_Jeongseon County":{"name":"Jeongseon County"},"KR_Gangwon-do_Pyeongchang County":{"name":"Pyeongchang County"},"KR_Gangwon-do_Samcheok":{"name":"Samcheok"},"KR_Gangwon-do_Sokcho":{"name":"Sokcho"},"KR_Gangwon-do_Taebaek":{"name":"Taebaek"},"KR_Gangwon-do_Wonju":{"name":"Wonju"},"KR_Gangwon-do_Yanggu County":{"name":"Yanggu County"},"KR_Gangwon-do_Yangyang County":{"name":"Yangyang County"},"KR_Gangwon-do_Yeongwol County":{"name":"Yeongwol County"}}},"KR_Gwangju":{"name":"Gwangju"},"KR_Gyeonggi-do":{"name":"Gyeonggi-do"},"KR_Gyeongsangbuk-do":{"name":"Gyeongsangbuk-do","regions":{"KR_Gyeongsangbuk-do_Buan County":{"name":"Buan County"},"KR_Gyeongsangbuk-do_Gimje":{"name":"Gimje"},"KR_Gyeongsangbuk-do_Gochang County":{"name":"Gochang County"},"KR_Gyeongsangbuk-do_Gunsan":{"name":"Gunsan"},"KR_Gyeongsangbuk-do_Iksan":{"name":"Iksan"},"KR_Gyeongsangbuk-do_Imsil County":{"name":"Imsil County"},"KR_Gyeongsangbuk-do_Jangsu County":{"name":"Jangsu County"},"KR_Gyeongsangbuk-do_Jeongeup":{"name":"Jeongeup"},"KR_Gyeongsangbuk-do_Jeonju":{"name":"Jeonju"},"KR_Gyeongsangbuk-do_Jinan County":{"name":"Jinan County"},"KR_Gyeongsangbuk-do_Muju County":{"name":"Muju County"},"KR_Gyeongsangbuk-do_Namwon":{"name":"Namwon"},"KR_Gyeongsangbuk-do_Sunchang County":{"name":"Sunchang County"},"KR_Gyeongsangbuk-do_Wanju County":{"name":"Wanju County"}}},"KR_Gyeongsangnam-do":{"name":"Gyeongsangnam-do","regions":{"KR_Gyeongsangnam-do_Boseong County":{"name":"Boseong County"},"KR_Gyeongsangnam-do_Damyang County":{"name":"Damyang County"},"KR_Gyeongsangnam-do_Gangjin County":{"name":"Gangjin County"},"KR_Gyeongsangnam-do_Goheung County":{"name":"Goheung County"},"KR_Gyeongsangnam-do_Gokseong County":{"name":"Gokseong County"},"KR_Gyeongsangnam-do_Gurye County":{"name":"Gurye County"},"KR_Gyeongsangnam-do_Gwangyang":{"name":"Gwangyang"},"KR_Gyeongsangnam-do_Haenam County":{"name":"Haenam County"},"KR_Gyeongsangnam-do_Hampyeong County":{"name":"Hampyeong County"},"KR_Gyeongsangnam-do_Hwasun County":{"name":"Hwasun County"},"KR_Gyeongsangnam-do_Jangheung County":{"name":"Jangheung County"},"KR_Gyeongsangnam-do_Jangseong County":{"name":"Jangseong County"},"KR_Gyeongsangnam-do_Jindo County":{"name":"Jindo County"},"KR_Gyeongsangnam-do_Mokpo":{"name":"Mokpo"},"KR_Gyeongsangnam-do_Muan County":{"name":"Muan County"},"KR_Gyeongsangnam-do_Naju":{"name":"Naju"},"KR_Gyeongsangnam-do_Sinan County":{"name":"Sinan County"},"KR_Gyeongsangnam-do_Suncheon":{"name":"Suncheon"},"KR_Gyeongsangnam-do_Wando County":{"name":"Wando County"},"KR_Gyeongsangnam-do_Yeongam County":{"name":"Yeongam County"},"KR_Gyeongsangnam-do_Yeonggwang County":{"name":"Yeonggwang County"},"KR_Gyeongsangnam-do_Yeosu":{"name":"Yeosu"}}},"KR_Incheon":{"name":"Incheon"},"KR_Jeju-do":{"name":"Jeju-do","regions":{"KR_Jeju-do_Ansan":{"name":"Ansan"},"KR_Jeju-do_Anseong":{"name":"Anseong"},"KR_Jeju-do_Anyang":{"name":"Anyang"},"KR_Jeju-do_Bucheon":{"name":"Bucheon"},"KR_Jeju-do_Dongducheon":{"name":"Dongducheon"},"KR_Jeju-do_Gapyeong County":{"name":"Gapyeong County"},"KR_Jeju-do_Gimpo":{"name":"Gimpo"},"KR_Jeju-do_Goyang":{"name":"Goyang"},"KR_Jeju-do_Gunpo":{"name":"Gunpo"},"KR_Jeju-do_Guri":{"name":"Guri"},"KR_Jeju-do_Gwacheon":{"name":"Gwacheon"},"KR_Jeju-do_Gwangju":{"name":"Gwangju"},"KR_Jeju-do_Gwangmyeong":{"name":"Gwangmyeong"},"KR_Jeju-do_Hanam":{"name":"Hanam"},"KR_Jeju-do_Hwaseong":{"name":"Hwaseong"},"KR_Jeju-do_Icheon":{"name":"Icheon"},"KR_Jeju-do_Namyangju":{"name":"Namyangju"},"KR_Jeju-do_Osan":{"name":"Osan"},"KR_Jeju-do_Paju":{"name":"Paju"},"KR_Jeju-do_Pocheon":{"name":"Pocheon"},"KR_Jeju-do_Pyeongtaek":{"name":"Pyeongtaek"},"KR_Jeju-do_Seongnam":{"name":"Seongnam"},"KR_Jeju-do_Siheung":{"name":"Siheung"},"KR_Jeju-do_Suwon":{"name":"Suwon"},"KR_Jeju-do_Uijeongbu":{"name":"Uijeongbu"},"KR_Jeju-do_Uiwang":{"name":"Uiwang"},"KR_Jeju-do_Yangju":{"name":"Yangju"},"KR_Jeju-do_Yangpyeong County":{"name":"Yangpyeong County"},"KR_Jeju-do_Yeoju County":{"name":"Yeoju County"},"KR_Jeju-do_Yeoncheon County":{"name":"Yeoncheon County"},"KR_Jeju-do_Yongin":{"name":"Yongin"}}},"KR_Jeollabuk-do":{"name":"Jeollabuk-do","regions":{"KR_Jeollabuk-do_Boeun County":{"name":"Boeun County"},"KR_Jeollabuk-do_Cheongju":{"name":"Cheongju"},"KR_Jeollabuk-do_Cheongwon County":{"name":"Cheongwon County"},"KR_Jeollabuk-do_Chungju":{"name":"Chungju"},"KR_Jeollabuk-do_Danyang County":{"name":"Danyang County"},"KR_Jeollabuk-do_Eumseong County":{"name":"Eumseong County"},"KR_Jeollabuk-do_Goesan County":{"name":"Goesan County"},"KR_Jeollabuk-do_Jecheon":{"name":"Jecheon"},"KR_Jeollabuk-do_Jeungpyeong County":{"name":"Jeungpyeong County"},"KR_Jeollabuk-do_Jincheon County":{"name":"Jincheon County"},"KR_Jeollabuk-do_Okcheon County":{"name":"Okcheon County"},"KR_Jeollabuk-do_Yeongdong County":{"name":"Yeongdong County"}}},"KR_Jeollanam-do":{"name":"Jeollanam-do","regions":{"KR_Jeollanam-do_Asan":{"name":"Asan"},"KR_Jeollanam-do_Boryeong":{"name":"Boryeong"},"KR_Jeollanam-do_Buyeo County":{"name":"Buyeo County"},"KR_Jeollanam-do_Cheonan":{"name":"Cheonan"},"KR_Jeollanam-do_Cheongyang County":{"name":"Cheongyang County"},"KR_Jeollanam-do_Dangjin County":{"name":"Dangjin County"},"KR_Jeollanam-do_Geumsan County":{"name":"Geumsan County"},"KR_Jeollanam-do_Gongju":{"name":"Gongju"},"KR_Jeollanam-do_Gyeryong":{"name":"Gyeryong"},"KR_Jeollanam-do_Hongseong County":{"name":"Hongseong County"},"KR_Jeollanam-do_Nonsan":{"name":"Nonsan"},"KR_Jeollanam-do_Seocheon County":{"name":"Seocheon County"},"KR_Jeollanam-do_Seosan":{"name":"Seosan"},"KR_Jeollanam-do_Taean County":{"name":"Taean County"},"KR_Jeollanam-do_Yeongi County":{"name":"Yeongi County"},"KR_Jeollanam-do_Yesan County":{"name":"Yesan County"}}},"KR_Seoul":{"name":"Seoul"},"KR_Ulsan":{"name":"Ulsan"}}},"CN":{"name":"China","regions":{"CN_Beijing":{"name":"Beijing","regions":{"CN_Beijing_Dongcheng":{"name":"Dongcheng"},"CN_Beijing_Xicheng":{"name":"Xicheng"},"CN_Beijing_Chaoyang":{"name":"Chaoyang"},"CN_Beijing_Haidian":{"name":"Haidian"},"CN_Beijing_Fengtai":{"name":"Fengtai"},"CN_Beijing_Shijingshan":{"name":"Shijingshan"},"CN_Beijing_Tongzhou":{"name":"Tongzhou"},"CN_Beijing_Shunyi":{"name":"Shunyi"},"CN_Beijing_Changping":{"name":"Changping"},"CN_Beijing_Daxing":{"name":"Daxing"},"CN_Beijing_Mentougou":{"name":"Mentougou"},"CN_Beijing_Fangshan":{"name":"Fangshan"},"CN_Beijing_Pinggu":{"name":"Pinggu"},"CN_Beijing_Huairou":{"name":"Huairou"},"CN_Beijing_Miyun County":{"name":"Miyun County"},"CN_Beijing_Yanqing County":{"name":"Yanqing County"}}},"CN_Chongqing":{"name":"Chongqing","regions":{"CN_Chongqing_Banan":{"name":"Banan"},"CN_Chongqing_Beibei":{"name":"Beibei"},"CN_Chongqing_Bishan":{"name":"Bishan"},"CN_Chongqing_Changshou":{"name":"Changshou"},"CN_Chongqing_Dadukou":{"name":"Dadukou"},"CN_Chongqing_Dazu":{"name":"Dazu"},"CN_Chongqing_Fuling":{"name":"Fuling"},"CN_Chongqing_Hechuan":{"name":"Hechuan"},"CN_Chongqing_Jiangbei":{"name":"Jiangbei"},"CN_Chongqing_Jiangjin":{"name":"Jiangjin"},"CN_Chongqing_Jiulongpo":{"name":"Jiulongpo"},"CN_Chongqing_Nan'an":{"name":"Nan'an"},"CN_Chongqing_Nanchuan":{"name":"Nanchuan"},"CN_Chongqing_Qianjiang":{"name":"Qianjiang"},"CN_Chongqing_Shapingba":{"name":"Shapingba"},"CN_Chongqing_Tongliang":{"name":"Tongliang"},"CN_Chongqing_Qijiang":{"name":"Qijiang"},"CN_Chongqing_Wanzhou":{"name":"Wanzhou"},"CN_Chongqing_Yubei":{"name":"Yubei"},"CN_Chongqing_Yongchuan":{"name":"Yongchuan"},"CN_Chongqing_Yuzhong":{"name":"Yuzhong"}}},"CN_Shanghai":{"name":"Shanghai","regions":{"CN_Shanghai_Huangpu":{"name":"Huangpu"},"CN_Shanghai_Xuhui":{"name":"Xuhui"},"CN_Shanghai_Changning":{"name":"Changning"},"CN_Shanghai_Jing'an":{"name":"Jing'an"},"CN_Shanghai_Putuo":{"name":"Putuo"},"CN_Shanghai_Zhabei":{"name":"Zhabei"},"CN_Shanghai_Hongkou":{"name":"Hongkou"},"CN_Shanghai_Yangpu":{"name":"Yangpu"},"CN_Shanghai_Pudong New":{"name":"Pudong New"},"CN_Shanghai_Baoshan":{"name":"Baoshan"},"CN_Shanghai_Minhang":{"name":"Minhang"},"CN_Shanghai_Jiading":{"name":"Jiading"},"CN_Shanghai_Jinshan":{"name":"Jinshan"},"CN_Shanghai_Songjiang":{"name":"Songjiang"},"CN_Shanghai_Qingpu":{"name":"Qingpu"},"CN_Shanghai_Fengxian":{"name":"Fengxian"},"CN_Shanghai_Chongming County":{"name":"Chongming County"}}},"CN_Tianjin":{"name":"Tianjin","regions":{"CN_Tianjin_Heping":{"name":"Heping"},"CN_Tianjin_Hexi":{"name":"Hexi"},"CN_Tianjin_Hebei":{"name":"Hebei"},"CN_Tianjin_Nankai":{"name":"Nankai"},"CN_Tianjin_Hedong":{"name":"Hedong"},"CN_Tianjin_Hongqiao":{"name":"Hongqiao"},"CN_Tianjin_Binhai New Area":{"name":"Binhai New Area"},"CN_Tianjin_Jinnan":{"name":"Jinnan"},"CN_Tianjin_Dongli":{"name":"Dongli"},"CN_Tianjin_Xiqing":{"name":"Xiqing"},"CN_Tianjin_Beichen":{"name":"Beichen"},"CN_Tianjin_Baodi":{"name":"Baodi"},"CN_Tianjin_Wuqing":{"name":"Wuqing"},"CN_Tianjin_Jixian":{"name":"Jixian"},"CN_Tianjin_Jinghai County":{"name":"Jinghai County"},"CN_Tianjin_Ninghe County":{"name":"Ninghe County"}}},"CN_Anhui":{"name":"Anhui","regions":{"CN_Anhui_Anqing":{"name":"Anqing"},"CN_Anhui_Bengbu":{"name":"Bengbu"},"CN_Anhui_Bozhou":{"name":"Bozhou"},"CN_Anhui_Chizhou":{"name":"Chizhou"},"CN_Anhui_Chuzhou":{"name":"Chuzhou"},"CN_Anhui_Fuyang":{"name":"Fuyang"},"CN_Anhui_Hefei":{"name":"Hefei"},"CN_Anhui_Huaibei":{"name":"Huaibei"},"CN_Anhui_Huainan":{"name":"Huainan"},"CN_Anhui_Huangshan":{"name":"Huangshan"},"CN_Anhui_Lu'an":{"name":"Lu'an"},"CN_Anhui_Ma'anshan":{"name":"Ma'anshan"},"CN_Anhui_Suzhou":{"name":"Suzhou"},"CN_Anhui_Tongling":{"name":"Tongling"},"CN_Anhui_Wuhu":{"name":"Wuhu"},"CN_Anhui_Xuancheng":{"name":"Xuancheng"}}},"CN_Fujian":{"name":"Fujian","regions":{"CN_Fujian_Fuzhou":{"name":"Fuzhou"},"CN_Fujian_Longyan":{"name":"Longyan"},"CN_Fujian_Nanping":{"name":"Nanping"},"CN_Fujian_Ningde":{"name":"Ningde"},"CN_Fujian_Putian":{"name":"Putian"},"CN_Fujian_Quanzhou":{"name":"Quanzhou"},"CN_Fujian_Sanming":{"name":"Sanming"},"CN_Fujian_Xiamen":{"name":"Xiamen"},"CN_Fujian_Zhangzhou":{"name":"Zhangzhou"}}},"CN_Gansu":{"name":"Gansu","regions":{"CN_Gansu_Baiyin":{"name":"Baiyin"},"CN_Gansu_Dingxi":{"name":"Dingxi"},"CN_Gansu_Jiayuguan":{"name":"Jiayuguan"},"CN_Gansu_Jinchang":{"name":"Jinchang"},"CN_Gansu_Jiuquan":{"name":"Jiuquan"},"CN_Gansu_Lanzhou":{"name":"Lanzhou"},"CN_Gansu_Longnan":{"name":"Longnan"},"CN_Gansu_Pingliang":{"name":"Pingliang"},"CN_Gansu_Qingyang":{"name":"Qingyang"},"CN_Gansu_Tianshui":{"name":"Tianshui"},"CN_Gansu_Wuwei":{"name":"Wuwei"},"CN_Gansu_Zhangye":{"name":"Zhangye"}}},"CN_Guangdong":{"name":"Guangdong","regions":{"CN_Guangdong_Chaozhou":{"name":"Chaozhou"},"CN_Guangdong_Dongguan":{"name":"Dongguan"},"CN_Guangdong_Foshan":{"name":"Foshan"},"CN_Guangdong_Guangzhou":{"name":"Guangzhou"},"CN_Guangdong_Heyuan":{"name":"Heyuan"},"CN_Guangdong_Huizhou":{"name":"Huizhou"},"CN_Guangdong_Jiangmen":{"name":"Jiangmen"},"CN_Guangdong_Jieyang":{"name":"Jieyang"},"CN_Guangdong_Maoming":{"name":"Maoming"},"CN_Guangdong_Meizhou":{"name":"Meizhou"},"CN_Guangdong_Qingyuan":{"name":"Qingyuan"},"CN_Guangdong_Shantou":{"name":"Shantou"},"CN_Guangdong_Shanwei":{"name":"Shanwei"},"CN_Guangdong_Shaoguan":{"name":"Shaoguan"},"CN_Guangdong_Shenzhen":{"name":"Shenzhen"},"CN_Guangdong_Yangjiang":{"name":"Yangjiang"},"CN_Guangdong_Yunfu":{"name":"Yunfu"},"CN_Guangdong_Zhanjiang":{"name":"Zhanjiang"},"CN_Guangdong_Zhaoqing":{"name":"Zhaoqing"},"CN_Guangdong_Zhongshan":{"name":"Zhongshan"},"CN_Guangdong_Zhuhai":{"name":"Zhuhai"}}},"CN_Guangxi":{"name":"Guangxi","regions":{"CN_Guangxi_Baise":{"name":"Baise"},"CN_Guangxi_Beihai":{"name":"Beihai"},"CN_Guangxi_Chongzuo":{"name":"Chongzuo"},"CN_Guangxi_Fangchenggang":{"name":"Fangchenggang"},"CN_Guangxi_Guigang":{"name":"Guigang"},"CN_Guangxi_Guilin":{"name":"Guilin"},"CN_Guangxi_Hechi":{"name":"Hechi"},"CN_Guangxi_Hezhou":{"name":"Hezhou"},"CN_Guangxi_Laibin":{"name":"Laibin"},"CN_Guangxi_Liuzhou":{"name":"Liuzhou"},"CN_Guangxi_Nanning":{"name":"Nanning"},"CN_Guangxi_Qinzhou":{"name":"Qinzhou"},"CN_Guangxi_Wuzhou":{"name":"Wuzhou"},"CN_Guangxi_Yulin":{"name":"Yulin"}}},"CN_Guizhou":{"name":"Guizhou","regions":{"CN_Guizhou_Anshun":{"name":"Anshun"},"CN_Guizhou_Bijie":{"name":"Bijie"},"CN_Guizhou_Guiyang":{"name":"Guiyang"},"CN_Guizhou_Liupanshui":{"name":"Liupanshui"},"CN_Guizhou_Tongren":{"name":"Tongren"},"CN_Guizhou_Zunyi":{"name":"Zunyi"},"CN_Guizhou_Kaili":{"name":"Kaili"}}},"CN_Hainan":{"name":"Hainan","regions":{"CN_Hainan_Danzhou":{"name":"Danzhou"},"CN_Hainan_Dongfang":{"name":"Dongfang"},"CN_Hainan_Haikou":{"name":"Haikou"},"CN_Hainan_Qionghai":{"name":"Qionghai"},"CN_Hainan_Sansha":{"name":"Sansha"},"CN_Hainan_Sanya":{"name":"Sanya"},"CN_Hainan_Wanning":{"name":"Wanning"},"CN_Hainan_Wenchang":{"name":"Wenchang"},"CN_Hainan_Wuzhishan":{"name":"Wuzhishan"}}},"CN_Hebei":{"name":"Hebei","regions":{"CN_Hebei_Baoding":{"name":"Baoding"},"CN_Hebei_Cangzhou":{"name":"Cangzhou"},"CN_Hebei_Chengde":{"name":"Chengde"},"CN_Hebei_Handan":{"name":"Handan"},"CN_Hebei_Hengshui":{"name":"Hengshui"},"CN_Hebei_Langfang":{"name":"Langfang"},"CN_Hebei_Qinhuangdao":{"name":"Qinhuangdao"},"CN_Hebei_Shijiazhuang":{"name":"Shijiazhuang"},"CN_Hebei_Tangshan":{"name":"Tangshan"},"CN_Hebei_Xingtai":{"name":"Xingtai"},"CN_Hebei_Zhangjiakou":{"name":"Zhangjiakou"}}},"CN_Heilongjiang":{"name":"Heilongjiang","regions":{"CN_Heilongjiang_Daqing":{"name":"Daqing"},"CN_Heilongjiang_Harbin":{"name":"Harbin"},"CN_Heilongjiang_Hegang":{"name":"Hegang"},"CN_Heilongjiang_Heihe":{"name":"Heihe"},"CN_Heilongjiang_Jiamusi":{"name":"Jiamusi"},"CN_Heilongjiang_Jixi":{"name":"Jixi"},"CN_Heilongjiang_Mudanjiang":{"name":"Mudanjiang"},"CN_Heilongjiang_Qiqihar":{"name":"Qiqihar"},"CN_Heilongjiang_Qitaihe":{"name":"Qitaihe"},"CN_Heilongjiang_Shuangyashan":{"name":"Shuangyashan"},"CN_Heilongjiang_Suihua":{"name":"Suihua"},"CN_Heilongjiang_Yichun":{"name":"Yichun"}}},"CN_Henan":{"name":"Henan","regions":{"CN_Henan_Anyang":{"name":"Anyang"},"CN_Henan_Hebi":{"name":"Hebi"},"CN_Henan_Jiaozuo":{"name":"Jiaozuo"},"CN_Henan_Jiyuan":{"name":"Jiyuan"},"CN_Henan_Kaifeng":{"name":"Kaifeng"},"CN_Henan_Luohe":{"name":"Luohe"},"CN_Henan_Luoyang":{"name":"Luoyang"},"CN_Henan_Nanyang":{"name":"Nanyang"},"CN_Henan_Pingdingshan":{"name":"Pingdingshan"},"CN_Henan_Puyang":{"name":"Puyang"},"CN_Henan_Sanmenxia":{"name":"Sanmenxia"},"CN_Henan_Shangqiu":{"name":"Shangqiu"},"CN_Henan_Xinxiang":{"name":"Xinxiang"},"CN_Henan_Xinyang":{"name":"Xinyang"},"CN_Henan_Xuchang":{"name":"Xuchang"},"CN_Henan_Zhengzhou":{"name":"Zhengzhou"},"CN_Henan_Zhoukou":{"name":"Zhoukou"},"CN_Henan_Zhumadian":{"name":"Zhumadian"}}},"CN_Hubei":{"name":"Hubei","regions":{"CN_Hubei_Ezhou":{"name":"Ezhou"},"CN_Hubei_Huanggang":{"name":"Huanggang"},"CN_Hubei_Huangshi":{"name":"Huangshi"},"CN_Hubei_Jingmen":{"name":"Jingmen"},"CN_Hubei_Jingzhou":{"name":"Jingzhou"},"CN_Hubei_Qianjiang":{"name":"Qianjiang"},"CN_Hubei_Shennongjia":{"name":"Shennongjia"},"CN_Hubei_Shiyan":{"name":"Shiyan"},"CN_Hubei_Suizhou":{"name":"Suizhou"},"CN_Hubei_Tianmen":{"name":"Tianmen"},"CN_Hubei_Wuhan":{"name":"Wuhan"},"CN_Hubei_Xiangyang":{"name":"Xiangyang"},"CN_Hubei_Xianning":{"name":"Xianning"},"CN_Hubei_Xiantao":{"name":"Xiantao"},"CN_Hubei_Xiaogan":{"name":"Xiaogan"},"CN_Hubei_Yichang":{"name":"Yichang"}}},"CN_Hunan":{"name":"Hunan","regions":{"CN_Hunan_Changde":{"name":"Changde"},"CN_Hunan_Changsha":{"name":"Changsha"},"CN_Hunan_Chenzhou":{"name":"Chenzhou"},"CN_Hunan_Hengyang":{"name":"Hengyang"},"CN_Hunan_Huaihua":{"name":"Huaihua"},"CN_Hunan_Loudi":{"name":"Loudi"},"CN_Hunan_Shaoyang":{"name":"Shaoyang"},"CN_Hunan_Xiangtan":{"name":"Xiangtan"},"CN_Hunan_Yiyang":{"name":"Yiyang"},"CN_Hunan_Yongzhou":{"name":"Yongzhou"},"CN_Hunan_Yueyang":{"name":"Yueyang"},"CN_Hunan_Zhangjiajie":{"name":"Zhangjiajie"},"CN_Hunan_Zhuzhou":{"name":"Zhuzhou"}}},"CN_Inner Mongolia":{"name":"Inner Mongolia","regions":{"CN_Inner Mongolia_Baotou":{"name":"Baotou"},"CN_Inner Mongolia_Bayannur":{"name":"Bayannur"},"CN_Inner Mongolia_Chifeng":{"name":"Chifeng"},"CN_Inner Mongolia_Hohhot":{"name":"Hohhot"},"CN_Inner Mongolia_Hulunbuir":{"name":"Hulunbuir"},"CN_Inner Mongolia_Ordos":{"name":"Ordos"},"CN_Inner Mongolia_Tongliao":{"name":"Tongliao"},"CN_Inner Mongolia_Ulanqab":{"name":"Ulanqab"},"CN_Inner Mongolia_Wuhai":{"name":"Wuhai"}}},"CN_Jiangsu":{"name":"Jiangsu","regions":{"CN_Jiangsu_Changzhou":{"name":"Changzhou"},"CN_Jiangsu_Huai'an":{"name":"Huai'an"},"CN_Jiangsu_Lianyungang":{"name":"Lianyungang"},"CN_Jiangsu_Nanjing":{"name":"Nanjing"},"CN_Jiangsu_Nantong":{"name":"Nantong"},"CN_Jiangsu_Suqian":{"name":"Suqian"},"CN_Jiangsu_Suzhou":{"name":"Suzhou"},"CN_Jiangsu_Taizhou":{"name":"Taizhou"},"CN_Jiangsu_Wuxi":{"name":"Wuxi"},"CN_Jiangsu_Xuzhou":{"name":"Xuzhou"},"CN_Jiangsu_Yancheng":{"name":"Yancheng"},"CN_Jiangsu_Yangzhou":{"name":"Yangzhou"},"CN_Jiangsu_Zhenjiang":{"name":"Zhenjiang"}}},"CN_Jiangxi":{"name":"Jiangxi","regions":{"CN_Jiangxi_Fuzhou":{"name":"Fuzhou"},"CN_Jiangxi_Ganzhou":{"name":"Ganzhou"},"CN_Jiangxi_Ji'an":{"name":"Ji'an"},"CN_Jiangxi_Jingdezhen":{"name":"Jingdezhen"},"CN_Jiangxi_Jiujiang":{"name":"Jiujiang"},"CN_Jiangxi_Nanchang":{"name":"Nanchang"},"CN_Jiangxi_Pingxiang":{"name":"Pingxiang"},"CN_Jiangxi_Shangrao":{"name":"Shangrao"},"CN_Jiangxi_Xinyu":{"name":"Xinyu"},"CN_Jiangxi_Yingtan":{"name":"Yingtan"},"CN_Jiangxi_Yichun":{"name":"Yichun"}}},"CN_Jilin":{"name":"Jilin","regions":{"CN_Jilin_Baicheng":{"name":"Baicheng"},"CN_Jilin_Baishan":{"name":"Baishan"},"CN_Jilin_Changchun":{"name":"Changchun"},"CN_Jilin_Jilin":{"name":"Jilin"},"CN_Jilin_Liaoyuan":{"name":"Liaoyuan"},"CN_Jilin_Siping":{"name":"Siping"},"CN_Jilin_Songyuan":{"name":"Songyuan"},"CN_Jilin_Tonghua":{"name":"Tonghua"}}},"CN_Liaoning":{"name":"Liaoning","regions":{"CN_Liaoning_Anshan":{"name":"Anshan"},"CN_Liaoning_Benxi":{"name":"Benxi"},"CN_Liaoning_Chaoyang":{"name":"Chaoyang"},"CN_Liaoning_Dalian":{"name":"Dalian"},"CN_Liaoning_Dandong":{"name":"Dandong"},"CN_Liaoning_Fushun":{"name":"Fushun"},"CN_Liaoning_Fuxin":{"name":"Fuxin"},"CN_Liaoning_Huludao":{"name":"Huludao"},"CN_Liaoning_Jinzhou":{"name":"Jinzhou"},"CN_Liaoning_Liaoyang":{"name":"Liaoyang"},"CN_Liaoning_Panjin":{"name":"Panjin"},"CN_Liaoning_Shenyang":{"name":"Shenyang"},"CN_Liaoning_Tieling":{"name":"Tieling"},"CN_Liaoning_Yingkou":{"name":"Yingkou"}}},"CN_Ningxia":{"name":"Ningxia","regions":{"CN_Ningxia_Guyuan":{"name":"Guyuan"},"CN_Ningxia_Shizuishan":{"name":"Shizuishan"},"CN_Ningxia_Wuzhong":{"name":"Wuzhong"},"CN_Ningxia_Yinchuan":{"name":"Yinchuan"},"CN_Ningxia_Zhongwei":{"name":"Zhongwei"}}},"CN_Qinghai":{"name":"Qinghai","regions":{"CN_Qinghai_Haidong":{"name":"Haidong"},"CN_Qinghai_Xining":{"name":"Xining"}}},"CN_Shaanxi":{"name":"Shaanxi","regions":{"CN_Shaanxi_Ankang":{"name":"Ankang"},"CN_Shaanxi_Baoji":{"name":"Baoji"},"CN_Shaanxi_Hanzhong":{"name":"Hanzhong"},"CN_Shaanxi_Shangluo":{"name":"Shangluo"},"CN_Shaanxi_Tongchuan":{"name":"Tongchuan"},"CN_Shaanxi_Xi'an":{"name":"Xi'an"},"CN_Shaanxi_Xianyang":{"name":"Xianyang"},"CN_Shaanxi_Weinan":{"name":"Weinan"},"CN_Shaanxi_Yan'an":{"name":"Yan'an"},"CN_Shaanxi_Yulin":{"name":"Yulin"}}},"CN_Shandong":{"name":"Shandong","regions":{"CN_Shandong_Binzhou":{"name":"Binzhou"},"CN_Shandong_Dezhou":{"name":"Dezhou"},"CN_Shandong_Dongying":{"name":"Dongying"},"CN_Shandong_Heze":{"name":"Heze"},"CN_Shandong_Jinan":{"name":"Jinan"},"CN_Shandong_Jining":{"name":"Jining"},"CN_Shandong_Laiwu":{"name":"Laiwu"},"CN_Shandong_Liaocheng":{"name":"Liaocheng"},"CN_Shandong_Linyi":{"name":"Linyi"},"CN_Shandong_Qingdao":{"name":"Qingdao"},"CN_Shandong_Rizhao":{"name":"Rizhao"},"CN_Shandong_Tai'an":{"name":"Tai'an"},"CN_Shandong_Weifang":{"name":"Weifang"},"CN_Shandong_Weihai":{"name":"Weihai"},"CN_Shandong_Yantai":{"name":"Yantai"},"CN_Shandong_Zaozhuang":{"name":"Zaozhuang"},"CN_Shandong_Zibo":{"name":"Zibo"}}},"CN_Shanxi":{"name":"Shanxi","regions":{"CN_Shanxi_Changzhi":{"name":"Changzhi"},"CN_Shanxi_Datong":{"name":"Datong"},"CN_Shanxi_Jincheng":{"name":"Jincheng"},"CN_Shanxi_Jinzhong":{"name":"Jinzhong"},"CN_Shanxi_Linfen":{"name":"Linfen"},"CN_Shanxi_Lüliang":{"name":"Lüliang"},"CN_Shanxi_Shuozhou":{"name":"Shuozhou"},"CN_Shanxi_Taiyuan":{"name":"Taiyuan"},"CN_Shanxi_Xinzhou":{"name":"Xinzhou"},"CN_Shanxi_Yangquan":{"name":"Yangquan"},"CN_Shanxi_Yuncheng":{"name":"Yuncheng"}}},"CN_Sichuan":{"name":"Sichuan","regions":{"CN_Sichuan_Bazhong":{"name":"Bazhong"},"CN_Sichuan_Chengdu":{"name":"Chengdu"},"CN_Sichuan_Dazhou":{"name":"Dazhou"},"CN_Sichuan_Deyang":{"name":"Deyang"},"CN_Sichuan_Guang'an":{"name":"Guang'an"},"CN_Sichuan_Guangyuan":{"name":"Guangyuan"},"CN_Sichuan_Leshan":{"name":"Leshan"},"CN_Sichuan_Luzhou":{"name":"Luzhou"},"CN_Sichuan_Meishan":{"name":"Meishan"},"CN_Sichuan_Mianyang":{"name":"Mianyang"},"CN_Sichuan_Neijiang":{"name":"Neijiang"},"CN_Sichuan_Nanchong":{"name":"Nanchong"},"CN_Sichuan_Panzhihua":{"name":"Panzhihua"},"CN_Sichuan_Suining":{"name":"Suining"},"CN_Sichuan_Ya'an":{"name":"Ya'an"},"CN_Sichuan_Yibin":{"name":"Yibin"},"CN_Sichuan_Zigong":{"name":"Zigong"},"CN_Sichuan_Ziyang":{"name":"Ziyang"}}},"CN_Tibet":{"name":"Tibet","regions":{"CN_Tibet_Lhasa":{"name":"Lhasa"},"CN_Tibet_Xigazê":{"name":"Xigazê"}}},"CN_Xinjiang":{"name":"Xinjiang","regions":{"CN_Xinjiang_Aral":{"name":"Aral"},"CN_Xinjiang_Aksu":{"name":"Aksu"},"CN_Xinjiang_Beitun":{"name":"Beitun"},"CN_Xinjiang_Karamay":{"name":"Karamay"},"CN_Xinjiang_Shihezi":{"name":"Shihezi"},"CN_Xinjiang_Shuanghe":{"name":"Shuanghe"},"CN_Xinjiang_Tumxuk":{"name":"Tumxuk"},"CN_Xinjiang_Korla":{"name":"Korla"},"CN_Xinjiang_Tiemenguan":{"name":"Tiemenguan"},"CN_Xinjiang_Ürümqi":{"name":"Ürümqi"},"CN_Xinjiang_Wujiaqu":{"name":"Wujiaqu"}}},"CN_Yunnan":{"name":"Yunnan","regions":{"CN_Yunnan_Baoshan":{"name":"Baoshan"},"CN_Yunnan_Kunming":{"name":"Kunming"},"CN_Yunnan_Lincang":{"name":"Lincang"},"CN_Yunnan_Lijiang":{"name":"Lijiang"},"CN_Yunnan_Dali":{"name":"Dali"},"CN_Yunnan_Pu'er":{"name":"Pu'er"},"CN_Yunnan_Qujing":{"name":"Qujing"},"CN_Yunnan_Yuxi":{"name":"Yuxi"},"CN_Yunnan_Zhaotong":{"name":"Zhaotong"}}},"CN_Zhejiang":{"name":"Zhejiang","regions":{"CN_Zhejiang_Hangzhou":{"name":"Hangzhou"},"CN_Zhejiang_Huzhou":{"name":"Huzhou"},"CN_Zhejiang_Jiaxing":{"name":"Jiaxing"},"CN_Zhejiang_Jinhua":{"name":"Jinhua"},"CN_Zhejiang_Lishui":{"name":"Lishui"},"CN_Zhejiang_Ningbo":{"name":"Ningbo"},"CN_Zhejiang_Quzhou":{"name":"Quzhou"},"CN_Zhejiang_Shaoxing":{"name":"Shaoxing"},"CN_Zhejiang_Taizhou":{"name":"Taizhou"},"CN_Zhejiang_Wenzhou":{"name":"Wenzhou"},"CN_Zhejiang_Zhoushan":{"name":"Zhoushan"}}}}},"IT":{"name":"Italy","regions":{"IT_Alessandria":{"name":"Alessandria"},"IT_Ancona":{"name":"Ancona"},"IT_Aosta":{"name":"Aosta"},"IT_Ascoli Piceno":{"name":"Ascoli Piceno"},"IT_Asti":{"name":"Asti"},"IT_Bari":{"name":"Bari"},"IT_Benevento":{"name":"Benevento"},"IT_Bergamo":{"name":"Bergamo"},"IT_Biella":{"name":"Biella"},"IT_Bologna":{"name":"Bologna"},"IT_Brescia":{"name":"Brescia"},"IT_Brindisi":{"name":"Brindisi"},"IT_Cagliari":{"name":"Cagliari"},"IT_Campobasso":{"name":"Campobasso"},"IT_Caserta":{"name":"Caserta"},"IT_Catania":{"name":"Catania"},"IT_Catanzaro":{"name":"Catanzaro"},"IT_Como":{"name":"Como"},"IT_Cosenza":{"name":"Cosenza"},"IT_Crotone":{"name":"Crotone"},"IT_Cuneo":{"name":"Cuneo"},"IT_Ferrara":{"name":"Ferrara"},"IT_Firenze":{"name":"Firenze"},"IT_Foggia":{"name":"Foggia"},"IT_Genova":{"name":"Genova"},"IT_Isernia":{"name":"Isernia"},"IT_L'Aquila":{"name":"L'Aquila"},"IT_La Spezia":{"name":"La Spezia"},"IT_Lecce":{"name":"Lecce"},"IT_Lecco":{"name":"Lecco"},"IT_Livorno":{"name":"Livorno"},"IT_Massa-Carrara":{"name":"Massa-Carrara"},"IT_Matera":{"name":"Matera"},"IT_Messina":{"name":"Messina"},"IT_Milano":{"name":"Milano"},"IT_Modena":{"name":"Modena"},"IT_Monza e Brianza":{"name":"Monza e Brianza"},"IT_Naples":{"name":"Naples"},"IT_Novara":{"name":"Novara"},"IT_Nuoro":{"name":"Nuoro"},"IT_Olbia-Tempio":{"name":"Olbia-Tempio"},"IT_Oristano":{"name":"Oristano"},"IT_Palermo":{"name":"Palermo"},"IT_Parma":{"name":"Parma"},"IT_Pavia":{"name":"Pavia"},"IT_Perugia":{"name":"Perugia"},"IT_Pisa":{"name":"Pisa"},"IT_Pordenone":{"name":"Pordenone"},"IT_Potenza":{"name":"Potenza"},"IT_Reggio Calabria":{"name":"Reggio Calabria"},"IT_Reggio Emilia":{"name":"Reggio Emilia"},"IT_Roma":{"name":"Roma"},"IT_Salerno":{"name":"Salerno"},"IT_Sassari":{"name":"Sassari"},"IT_Savona":{"name":"Savona"},"IT_Siena":{"name":"Siena"},"IT_Syracuse":{"name":"Syracuse"},"IT_Taranto":{"name":"Taranto"},"IT_Trapani":{"name":"Trapani"},"IT_Trento":{"name":"Trento"},"IT_Trieste":{"name":"Trieste"},"IT_Turin":{"name":"Turin"},"IT_Udine":{"name":"Udine"},"IT_Venice":{"name":"Venice"},"IT_Vercelli":{"name":"Vercelli"},"IT_Viterbo":{"name":"Viterbo"}}},"MY":{"name":"Malaysia","regions":{"MY_Johor":{"name":"Johor","regions":{"MY_Johor_Batu Pahat":{"name":"Batu Pahat"},"MY_Johor_Johor Bahru":{"name":"Johor Bahru"},"MY_Johor_Kluang":{"name":"Kluang"},"MY_Johor_Kota Tinggi":{"name":"Kota Tinggi"},"MY_Johor_Mersing":{"name":"Mersing"},"MY_Johor_Muar":{"name":"Muar"},"MY_Johor_Pontian":{"name":"Pontian"},"MY_Johor_Segamat":{"name":"Segamat"}}},"MY_Kedah":{"name":"Kedah","regions":{"MY_Kedah_Baling":{"name":"Baling"},"MY_Kedah_Bandar Baharu":{"name":"Bandar Baharu"},"MY_Kedah_Kota Setar":{"name":"Kota Setar"},"MY_Kedah_Kuala Muda":{"name":"Kuala Muda"},"MY_Kedah_Kubang Pasu":{"name":"Kubang Pasu"},"MY_Kedah_Kulim":{"name":"Kulim"},"MY_Kedah_Langkawi":{"name":"Langkawi"},"MY_Kedah_Padang Terap":{"name":"Padang Terap"},"MY_Kedah_Pendang":{"name":"Pendang"}}},"MY_Kelantan":{"name":"Kelantan","regions":{"MY_Kelantan_Bachok":{"name":"Bachok"},"MY_Kelantan_Gua Musang":{"name":"Gua Musang"},"MY_Kelantan_Jeli":{"name":"Jeli"},"MY_Kelantan_Kota Bharu":{"name":"Kota Bharu"},"MY_Kelantan_Kuala Krai":{"name":"Kuala Krai"},"MY_Kelantan_Machang":{"name":"Machang"},"MY_Kelantan_Pasir Mas":{"name":"Pasir Mas"},"MY_Kelantan_Pasir Putih":{"name":"Pasir Putih"},"MY_Kelantan_Tanah Merah":{"name":"Tanah Merah"},"MY_Kelantan_Tumpat":{"name":"Tumpat"}}},"MY_Kuala Lumpur":{"name":"Kuala Lumpur","regions":{"MY_Kuala Lumpur_Kuala Lumpur":{"name":"Kuala Lumpur"}}},"MY_Labuan":{"name":"Labuan","regions":{"MY_Labuan_Labuan":{"name":"Labuan"},"MY_Labuan_Victoria":{"name":"Victoria"}}},"MY_Malacca":{"name":"Malacca","regions":{"MY_Malacca_Alor Gajah":{"name":"Alor Gajah"},"MY_Malacca_Jasin":{"name":"Jasin"},"MY_Malacca_Melaka":{"name":"Melaka"}}},"MY_Negeri Sembilan":{"name":"Negeri Sembilan","regions":{"MY_Negeri Sembilan_Jelebu":{"name":"Jelebu"},"MY_Negeri Sembilan_Jempol":{"name":"Jempol"},"MY_Negeri Sembilan_Kuala Pilah":{"name":"Kuala Pilah"},"MY_Negeri Sembilan_Port Dickson":{"name":"Port Dickson"},"MY_Negeri Sembilan_Rembau":{"name":"Rembau"},"MY_Negeri Sembilan_Seremban":{"name":"Seremban"},"MY_Negeri Sembilan_Tampin":{"name":"Tampin"}}},"MY_Pahang":{"name":"Pahang","regions":{"MY_Pahang_Bentong":{"name":"Bentong"},"MY_Pahang_Bera":{"name":"Bera"},"MY_Pahang_Cameron Highlands":{"name":"Cameron Highlands"},"MY_Pahang_Jerantut":{"name":"Jerantut"},"MY_Pahang_Kuala Lipis":{"name":"Kuala Lipis"},"MY_Pahang_Kuantan":{"name":"Kuantan"},"MY_Pahang_Maran":{"name":"Maran"},"MY_Pahang_Pekan":{"name":"Pekan"},"MY_Pahang_Raub":{"name":"Raub"},"MY_Pahang_Rompin":{"name":"Rompin"},"MY_Pahang_Temerloh":{"name":"Temerloh"}}},"MY_Perak":{"name":"Perak","regions":{"MY_Perak_Batu Gajah":{"name":"Batu Gajah"},"MY_Perak_Ipoh":{"name":"Ipoh"},"MY_Perak_Kuala Kangsar":{"name":"Kuala Kangsar"},"MY_Perak_Lumut":{"name":"Lumut"},"MY_Perak_Sungai Siput":{"name":"Sungai Siput"},"MY_Perak_Taiping":{"name":"Taiping"},"MY_Perak_Tanjung Malim":{"name":"Tanjung Malim"},"MY_Perak_Teluk Intan":{"name":"Teluk Intan"}}},"MY_Perlis":{"name":"Perlis","regions":{"MY_Perlis_Kangar":{"name":"Kangar"}}},"MY_Pulau Pinang":{"name":"Pulau Pinang","regions":{"MY_Pulau Pinang_Bukit Mertajam":{"name":"Bukit Mertajam"},"MY_Pulau Pinang_Butterworth":{"name":"Butterworth"},"MY_Pulau Pinang_George Town":{"name":"George Town"},"MY_Pulau Pinang_Nibong Tebal":{"name":"Nibong Tebal"}}},"MY_Sabah":{"name":"Sabah","regions":{"MY_Sabah_Beaufort":{"name":"Beaufort"},"MY_Sabah_Beluran":{"name":"Beluran"},"MY_Sabah_Keningau":{"name":"Keningau"},"MY_Sabah_Kinabatangan":{"name":"Kinabatangan"},"MY_Sabah_Kota Belud":{"name":"Kota Belud"},"MY_Sabah_Kota Kinabalu":{"name":"Kota Kinabalu"},"MY_Sabah_Kota Marudu":{"name":"Kota Marudu"},"MY_Sabah_Kuala Penyu":{"name":"Kuala Penyu"},"MY_Sabah_Kudat":{"name":"Kudat"},"MY_Sabah_Kunak":{"name":"Kunak"},"MY_Sabah_Lahad Datu":{"name":"Lahad Datu"},"MY_Sabah_Nabawan":{"name":"Nabawan"},"MY_Sabah_Papar":{"name":"Papar"},"MY_Sabah_Penampang":{"name":"Penampang"},"MY_Sabah_Pitas":{"name":"Pitas"},"MY_Sabah_Ranau":{"name":"Ranau"},"MY_Sabah_Sandakan":{"name":"Sandakan"},"MY_Sabah_Semporna":{"name":"Semporna"},"MY_Sabah_Sipitang":{"name":"Sipitang"},"MY_Sabah_Tambunan":{"name":"Tambunan"},"MY_Sabah_Tawau":{"name":"Tawau"},"MY_Sabah_Tenom":{"name":"Tenom"},"MY_Sabah_Tuaran":{"name":"Tuaran"}}},"MY_Sarawak":{"name":"Sarawak","regions":{"MY_Sarawak_Betong":{"name":"Betong"},"MY_Sarawak_Bintulu":{"name":"Bintulu"},"MY_Sarawak_Kapit":{"name":"Kapit"},"MY_Sarawak_Kuching":{"name":"Kuching"},"MY_Sarawak_Limbang":{"name":"Limbang"},"MY_Sarawak_Miri":{"name":"Miri"},"MY_Sarawak_Mukah":{"name":"Mukah"},"MY_Sarawak_Samarahan":{"name":"Samarahan"},"MY_Sarawak_Sarikei":{"name":"Sarikei"},"MY_Sarawak_Sibu":{"name":"Sibu"},"MY_Sarawak_Sri Aman":{"name":"Sri Aman"}}},"MY_Selangor":{"name":"Selangor","regions":{"MY_Selangor_Gombak":{"name":"Gombak"},"MY_Selangor_Hulu Langat":{"name":"Hulu Langat"},"MY_Selangor_Hulu Selangor":{"name":"Hulu Selangor"},"MY_Selangor_Kuala Langat":{"name":"Kuala Langat"},"MY_Selangor_Kuala Selangor":{"name":"Kuala Selangor"},"MY_Selangor_Petaling":{"name":"Petaling"},"MY_Selangor_Sabak Bernam":{"name":"Sabak Bernam"},"MY_Selangor_Sepang":{"name":"Sepang"}}},"MY_Terengganu":{"name":"Terengganu","regions":{"MY_Terengganu_Besut":{"name":"Besut"},"MY_Terengganu_Dungun":{"name":"Dungun"},"MY_Terengganu_Hulu":{"name":"Hulu"},"MY_Terengganu_Kemaman":{"name":"Kemaman"},"MY_Terengganu_Kuala Terengganu":{"name":"Kuala Terengganu"},"MY_Terengganu_Marang":{"name":"Marang"},"MY_Terengganu_Setiu":{"name":"Setiu"}}}}},"NZ":{"name":"New Zealand","regions":{"NZ_Auckland":{"name":"Auckland"},"NZ_Blenheim":{"name":"Blenheim"},"NZ_Christchurch":{"name":"Christchurch"},"NZ_Dunedin":{"name":"Dunedin"},"NZ_Far North":{"name":"Far North"},"NZ_Gisborne":{"name":"Gisborne"},"NZ_Greymouth":{"name":"Greymouth"},"NZ_Hamilton":{"name":"Hamilton"},"NZ_Hastings":{"name":"Hastings"},"NZ_Invercargill":{"name":"Invercargill"},"NZ_Kaipara":{"name":"Kaipara"},"NZ_Manukau":{"name":"Manukau"},"NZ_Napier":{"name":"Napier"},"NZ_Nelson":{"name":"Nelson"},"NZ_New Plymouth":{"name":"New Plymouth"},"NZ_North Shore":{"name":"North Shore"},"NZ_Palmerston North":{"name":"Palmerston North"},"NZ_Richmond":{"name":"Richmond"},"NZ_Stratford":{"name":"Stratford"},"NZ_Taumarunui":{"name":"Taumarunui"},"NZ_Waitakere":{"name":"Waitakere"},"NZ_Wanganui":{"name":"Wanganui"},"NZ_Whakatane":{"name":"Whakatane"},"NZ_Whangarei":{"name":"Whangarei"}}},"FR":{"name":"France","regions":{"FR_Aix-en-Provence":{"name":"Aix-en-Provence"},"FR_Ajaccio":{"name":"Ajaccio"},"FR_Amiens":{"name":"Amiens"},"FR_Arles":{"name":"Arles"},"FR_Besancon":{"name":"Besancon"},"FR_Caen":{"name":"Caen"},"FR_Chalons-en-Champagne":{"name":"Chalons-en-Champagne"},"FR_Dijon":{"name":"Dijon"},"FR_Frejus":{"name":"Fréjus"},"FR_Lille":{"name":"Lille"},"FR_Limoges":{"name":"Limoges"},"FR_Lyon":{"name":"Lyon"},"FR_Marseille":{"name":"Marseille"},"FR_Metz":{"name":"Metz"},"FR_Montpellier":{"name":"Montpellier"},"FR_Nantes":{"name":"Nantes"},"FR_Nice":{"name":"Nice"},"FR_Orleans":{"name":"Orleans"},"FR_Paris":{"name":"Paris"},"FR_Rennes":{"name":"Rennes"},"FR_Rouen":{"name":"Rouen"},"FR_Toulouse":{"name":"Toulouse"},"FR_Valence":{"name":"Valence"}}},"AT":{"name":"Austria","regions":{"AT_Burgenland":{"name":"Burgenland"},"AT_Carinthia":{"name":"Carinthia"},"AT_Lower Austria":{"name":"Lower Austria"},"AT_Salzburg":{"name":"Salzburg"},"AT_Styria":{"name":"Styria"},"AT_Tyrol":{"name":"Tyrol"},"AT_Upper Austria":{"name":"Upper Austria"},"AT_Vienna":{"name":"Vienna"},"AT_Vorarlberg":{"name":"Vorarlberg"}}},"SG":{"name":"Singapore"},"TH":{"name":"Thailand","regions":{"TH_Amnat Charoen":{"name":"Amnat Charoen"},"TH_Ang Thong":{"name":"Ang Thong"},"TH_Bangkok":{"name":"Bangkok"},"TH_Buri Ram":{"name":"Buri Ram"},"TH_Chachoengsao":{"name":"Chachoengsao"},"TH_Chai Nat":{"name":"Chai Nat"},"TH_Chaiyaphum":{"name":"Chaiyaphum"},"TH_Chanthaburi":{"name":"Chanthaburi"},"TH_Chiang Mai":{"name":"Chiang Mai"},"TH_Chiang Rai":{"name":"Chiang Rai"},"TH_Chon Buri":{"name":"Chon Buri"},"TH_Chumphon":{"name":"Chumphon"},"TH_Kalasin":{"name":"Kalasin"},"TH_Kamphaeng Phet":{"name":"Kamphaeng Phet"},"TH_Kanchanaburi":{"name":"Kanchanaburi"},"TH_Khon Kaen":{"name":"Khon Kaen"},"TH_Krabi":{"name":"Krabi"},"TH_Lamphun":{"name":"Lamphun"},"TH_Loei":{"name":"Loei"},"TH_Lop Buri":{"name":"Lop Buri"},"TH_Mae Hong Son":{"name":"Mae Hong Son"},"TH_Maha Sarakham":{"name":"Maha Sarakham"},"TH_Mukdahan":{"name":"Mukdahan"},"TH_Nakhon Nayok":{"name":"Nakhon Nayok"},"TH_Nakhon Pathom":{"name":"Nakhon Pathom"},"TH_Nakhon Phanom":{"name":"Nakhon Phanom"},"TH_Nakhon Sawan":{"name":"Nakhon Sawan"},"TH_Nakhon Si Thammarat":{"name":"Nakhon Si Thammarat"},"TH_Nan":{"name":"Nan"},"TH_Narathiwat":{"name":"Narathiwat"},"TH_Nong Bua Lamphu":{"name":"Nong Bua Lamphu"},"TH_Nong Khai":{"name":"Nong Khai"},"TH_Nonthaburi":{"name":"Nonthaburi"},"TH_Pathum Thani":{"name":"Pathum Thani"},"TH_Pattani":{"name":"Pattani"},"TH_Phangnga":{"name":"Phangnga"},"TH_Phatthalung":{"name":"Phatthalung"},"TH_Phayao":{"name":"Phayao"},"TH_Phetchabun":{"name":"Phetchabun"},"TH_Phetchaburi":{"name":"Phetchaburi"},"TH_Phichit":{"name":"Phichit"},"TH_Phitsanulok":{"name":"Phitsanulok"},"TH_Phra Nakhon Si Ayutthaya":{"name":"Phra Nakhon Si Ayutthaya"},"TH_Phrae":{"name":"Phrae"},"TH_Phuket":{"name":"Phuket"},"TH_Prachin Buri":{"name":"Prachin Buri"},"TH_Prachuap Khiri Khan":{"name":"Prachuap Khiri Khan"},"TH_Ranong":{"name":"Ranong"},"TH_Ratchaburi":{"name":"Ratchaburi"},"TH_Rayong":{"name":"Rayong"},"TH_Roi Et":{"name":"Roi Et"},"TH_Sa Kaeo":{"name":"Sa Kaeo"},"TH_Sakon Nakhon":{"name":"Sakon Nakhon"},"TH_Samut Prakan":{"name":"Samut Prakan"},"TH_Samut Sakhon":{"name":"Samut Sakhon"},"TH_Samut Songkhram":{"name":"Samut Songkhram"},"TH_Saraburi":{"name":"Saraburi"},"TH_Satun":{"name":"Satun"},"TH_Si sa ket":{"name":"Si sa ket"},"TH_Sing Buri":{"name":"Sing Buri"},"TH_Songkhla":{"name":"Songkhla"},"TH_Sukhothai":{"name":"Sukhothai"},"TH_Suphan Buri":{"name":"Suphan Buri"},"TH_Surat Thani":{"name":"Surat Thani"},"TH_Surin":{"name":"Surin"},"TH_Tak":{"name":"Tak"},"TH_Trang":{"name":"Trang"},"TH_Trat":{"name":"Trat"},"TH_Ubon Ratchathani":{"name":"Ubon Ratchathani"},"TH_Udon Thani":{"name":"Udon Thani"},"TH_Uthai Thani":{"name":"Uthai Thani"},"TH_Uttaradit":{"name":"Uttaradit"},"TH_Yala":{"name":"Yala"},"TH_Yasothon":{"name":"Yasothon"}}},"AU":{"name":"Australia","regions":{"AU_Canberra":{"name":"Canberra"},"AU_New South Wales":{"name":"New South Wales","regions":{"AU_New South Wales_Newcastle":{"name":"Newcastle"},"AU_New South Wales_Sydney":{"name":"Sydney"},"AU_New South Wales_Wollongong":{"name":"Wollongong"}}},"AU_Northern Territory":{"name":"Northern Territory","regions":{"AU_Northern Territory_Darwin":{"name":"Darwin"},"AU_Northern Territory_Palmerston":{"name":"Palmerston"}}},"AU_Queensland":{"name":"Queensland","regions":{"AU_Queensland_Brisbane":{"name":"Brisbane"},"AU_Queensland_Cairns":{"name":"Cairns"},"AU_Queensland_Caloundra":{"name":"Caloundra"},"AU_Queensland_Gold Coast":{"name":"Gold Coast"},"AU_Queensland_Toowoomba":{"name":"Toowoomba"},"AU_Queensland_Townsville":{"name":"Townsville"}}},"AU_South Australia":{"name":"South Australia","regions":{"AU_South Australia_Adelaide":{"name":"Adelaide"},"AU_South Australia_Mount Gambier":{"name":"Mount Gambier"},"AU_South Australia_Murray Bridge":{"name":"Murray Bridge"},"AU_South Australia_Port Augusta":{"name":"Port Augusta"},"AU_South Australia_Port Lincoln":{"name":"Port Lincoln"},"AU_South Australia_Port Pirie":{"name":"Port Pirie"},"AU_South Australia_Victor Harbor":{"name":"Victor Harbor"},"AU_South Australia_Whyalla":{"name":"Whyalla"}}},"AU_Tasmania":{"name":"Tasmania","regions":{"AU_Tasmania_Burnie":{"name":"Burnie"},"AU_Tasmania_Devonport":{"name":"Devonport"},"AU_Tasmania_Hobart":{"name":"Hobart"},"AU_Tasmania_Launceston":{"name":"Launceston"}}},"AU_Victoria":{"name":"Victoria","regions":{"AU_Victoria_Geelong":{"name":"Geelong"},"AU_Victoria_Melbourne":{"name":"Melbourne"}}},"AU_Western Australia":{"name":"Western Australia","regions":{"AU_Western Australia_Albany":{"name":"Albany"},"AU_Western Australia_Bunbury":{"name":"Bunbury"},"AU_Western Australia_Fremantle":{"name":"Fremantle"},"AU_Western Australia_Geraldton":{"name":"Geraldton"},"AU_Western Australia_Kalgoorlie":{"name":"Kalgoorlie"},"AU_Western Australia_Mandurah":{"name":"Mandurah"},"AU_Western Australia_Perth":{"name":"Perth"}}}}},"GB":{"name":"United Kingdom","regions":{"GB_England":{"name":"England","regions":{"GB_England_Bath":{"name":"Bath"},"GB_England_Birmingham":{"name":"Birmingham"},"GB_England_Bradford":{"name":"Bradford"},"GB_England_Brighton & Hove":{"name":"Brighton & Hove"},"GB_England_Bristol":{"name":"Bristol"},"GB_England_Cambridge":{"name":"Cambridge"},"GB_England_Canterbury":{"name":"Canterbury"},"GB_England_Carlisle":{"name":"Carlisle"},"GB_England_Chester":{"name":"Chester"},"GB_England_Chichester":{"name":"Chichester"},"GB_England_Coventry":{"name":"Coventry"},"GB_England_Derby":{"name":"Derby"},"GB_England_Durham":{"name":"Durham"},"GB_England_Ely":{"name":"Ely"},"GB_England_Exeter":{"name":"Exeter"},"GB_England_Gloucester":{"name":"Gloucester"},"GB_England_Hereford":{"name":"Hereford"},"GB_England_Kingston upon Hull":{"name":"Kingston upon Hull"},"GB_England_Lancaster":{"name":"Lancaster"},"GB_England_Leeds":{"name":"Leeds"},"GB_England_Leicester":{"name":"Leicester"},"GB_England_Lichfield":{"name":"Lichfield"},"GB_England_Lincoln":{"name":"Lincoln"},"GB_England_Liverpool":{"name":"Liverpool"},"GB_England_London":{"name":"London"},"GB_England_Manchester":{"name":"Manchester"},"GB_England_Newcastle":{"name":"Newcastle"},"GB_England_Norwich":{"name":"Norwich"},"GB_England_Nottingham":{"name":"Nottingham"},"GB_England_Oxford":{"name":"Oxford"},"GB_England_Peterborough":{"name":"Peterborough"},"GB_England_Plymouth":{"name":"Plymouth"},"GB_England_Portsmouth":{"name":"Portsmouth"},"GB_England_Preston":{"name":"Preston"},"GB_England_Ripon":{"name":"Ripon"},"GB_England_Saint Albans":{"name":"Saint Albans"},"GB_England_Salford":{"name":"Salford"},"GB_England_Salisbury":{"name":"Salisbury"},"GB_England_Sheffield":{"name":"Sheffield"},"GB_England_Southampton":{"name":"Southampton"},"GB_England_Stoke-on-Trent":{"name":"Stoke-on-Trent"},"GB_England_Sunderland":{"name":"Sunderland"},"GB_England_Truro":{"name":"Truro"},"GB_England_Wakefield":{"name":"Wakefield"},"GB_England_Wells":{"name":"Wells"},"GB_England_Winchester":{"name":"Winchester"},"GB_England_Wolverhampton":{"name":"Wolverhampton"},"GB_England_Worcester":{"name":"Worcester"},"GB_England_York":{"name":"York"}}},"GB_Northern Ireland":{"name":"Northern Ireland","regions":{"GB_Northern Ireland_Belfast":{"name":"Belfast"},"GB_Northern Ireland_Derry":{"name":"Derry"},"GB_Northern Ireland_Lisburn":{"name":"Lisburn"},"GB_Northern Ireland_Newry":{"name":"Newry"}}},"GB_Scotland":{"name":"Scotland","regions":{"GB_Scotland_Aberdeen":{"name":"Aberdeen"},"GB_Scotland_Dundee":{"name":"Dundee"},"GB_Scotland_Edinburgh":{"name":"Edinburgh"},"GB_Scotland_Glasgow":{"name":"Glasgow"},"GB_Scotland_Inverness":{"name":"Inverness"},"GB_Scotland_Stirling":{"name":"Stirling"}}},"GB_Wales":{"name":"Wales","regions":{"GB_Wales_Bangor":{"name":"Bangor"},"GB_Wales_Cardiff":{"name":"Cardiff"},"GB_Wales_Newport":{"name":"Newport"},"GB_Wales_Swansea":{"name":"Swansea"}}}}},"US":{"name":"United States","regions":{"US_Alabama":{"name":"Alabama","abbr":"AL","regions":{"US_Alabama_Birmingham":{"name":"Birmingham"},"US_Alabama_Mobile":{"name":"Mobile"},"US_Alabama_Montgomery":{"name":"Montgomery"}}},"US_Alaska":{"name":"Alaska","abbr":"AK","regions":{"US_Alaska_Anchorage":{"name":"Anchorage"},"US_Alaska_Fairbanks":{"name":"Fairbanks"},"US_Alaska_Juneau":{"name":"Juneau"}}},"US_Arizona":{"name":"Arizona","abbr":"AZ","regions":{"US_Arizona_Glendale":{"name":"Glendale"},"US_Arizona_Mesa":{"name":"Mesa"},"US_Arizona_Phoenix":{"name":"Phoenix"},"US_Arizona_Scottsdale":{"name":"Scottsdale"},"US_Arizona_Tempe":{"name":"Tempe"},"US_Arizona_Tucson":{"name":"Tucson"},"US_Arizona_Yuma":{"name":"Yuma"}}},"US_Arkansas":{"name":"Arkansas","abbr":"AR","regions":{"US_Arkansas_Fayetteville":{"name":"Fayetteville"},"US_Arkansas_Fort Smith":{"name":"Fort Smith"},"US_Arkansas_Little Rock":{"name":"Little Rock"}}},"US_California":{"name":"California","abbr":"CA","regions":{"US_California_Los Angeles":{"name":"Los Angeles"},"US_California_San Diego":{"name":"San Diego"},"US_California_San Francisco":{"name":"San Francisco"},"US_California_San Jose":{"name":"San Jose"}}},"US_Colorado":{"name":"Colorado","abbr":"CO","regions":{"US_Colorado_Aspen":{"name":"Aspen"},"US_Colorado_Aurora":{"name":"Aurora"},"US_Colorado_Boulder":{"name":"Boulder"},"US_Colorado_Colorado Springs":{"name":"Colorado Springs"},"US_Colorado_Denver":{"name":"Denver"},"US_Colorado_Fort Collins":{"name":"Fort Collins"},"US_Colorado_Grand Junction":{"name":"Grand Junction"},"US_Colorado_Vail":{"name":"Vail"}}},"US_Connecticut":{"name":"Connecticut","abbr":"CT","regions":{"US_Connecticut_Bridgeport":{"name":"Bridgeport"},"US_Connecticut_Darien":{"name":"Darien"},"US_Connecticut_Greenwich":{"name":"Greenwich"},"US_Connecticut_Hartford":{"name":"Hartford"},"US_Connecticut_Middletown":{"name":"Middletown"},"US_Connecticut_New Britain":{"name":"New Britain"},"US_Connecticut_New Haven":{"name":"New Haven"},"US_Connecticut_Waterbury":{"name":"Waterbury"},"US_Connecticut_Westport":{"name":"Westport"}}},"US_Delaware":{"name":"Delaware","abbr":"DE","regions":{"US_Delaware_Dover":{"name":"Dover"},"US_Delaware_Newark":{"name":"Newark"},"US_Delaware_Wilmington":{"name":"Wilmington"}}},"US_District of Columbia":{"name":"District of Columbia","abbr":"DC","regions":{"US_District of Columbia_Washington D.C.":{"name":"Washington D.C."}}},"US_Florida":{"name":"Florida","abbr":"FL","regions":{"US_Florida_Cape Canaveral":{"name":"Cape Canaveral"},"US_Florida_Fort Lauderdale":{"name":"Fort Lauderdale"},"US_Florida_Jacksonville":{"name":"Jacksonville"},"US_Florida_Key West":{"name":"Key West"},"US_Florida_Miami":{"name":"Miami"},"US_Florida_Orlando":{"name":"Orlando"},"US_Florida_St. Petersburg":{"name":"St. Petersburg"},"US_Florida_Tallahassee":{"name":"Tallahassee"},"US_Florida_Tampa":{"name":"Tampa"}}},"US_Georgia":{"name":"Georgia","abbr":"GA","regions":{"US_Georgia_Atlanta":{"name":"Atlanta"},"US_Georgia_Augusta":{"name":"Augusta"},"US_Georgia_Columbus":{"name":"Columbus"},"US_Georgia_Macon":{"name":"Macon"},"US_Georgia_Savannah":{"name":"Savannah"}}},"US_Hawaii":{"name":"Hawaii","abbr":"HI","regions":{"US_Hawaii_Hilo":{"name":"Hilo"},"US_Hawaii_Honolulu":{"name":"Honolulu"},"US_Hawaii_Kailua":{"name":"Kailua"}}},"US_Idaho":{"name":"Idaho","abbr":"ID","regions":{"US_Idaho_American Falls":{"name":"American Falls"},"US_Idaho_Blackfoot":{"name":"Blackfoot"},"US_Idaho_Boise":{"name":"Boise"},"US_Idaho_Coeur d'Alene":{"name":"Coeur d'Alene"},"US_Idaho_Idaho Falls":{"name":"Idaho Falls"},"US_Idaho_Ketchum":{"name":"Ketchum"},"US_Idaho_Lewiston":{"name":"Lewiston"},"US_Idaho_Moscow":{"name":"Moscow"},"US_Idaho_Murphy":{"name":"Murphy"},"US_Idaho_Nampa":{"name":"Nampa"},"US_Idaho_Pocatello":{"name":"Pocatello"},"US_Idaho_Sun Valley":{"name":"Sun Valley"}}},"US_Illinois":{"name":"Illinois","abbr":"IL","regions":{"US_Illinois_Alton":{"name":"Alton"},"US_Illinois_Aurora":{"name":"Aurora"},"US_Illinois_Bloomington":{"name":"Bloomington"},"US_Illinois_Carbondale":{"name":"Carbondale"},"US_Illinois_Centralia":{"name":"Centralia"},"US_Illinois_Champaign-Urbana":{"name":"Champaign-Urbana"},"US_Illinois_Chicago":{"name":"Chicago"},"US_Illinois_Danville":{"name":"Danville"},"US_Illinois_De Kalb":{"name":"De Kalb"},"US_Illinois_Decatur":{"name":"Decatur"},"US_Illinois_East St Louis":{"name":"East St Louis"},"US_Illinois_Galesburg":{"name":"Galesburg"},"US_Illinois_Normal":{"name":"Normal"},"US_Illinois_Peoria":{"name":"Peoria"},"US_Illinois_Rock Island":{"name":"Rock Island"},"US_Illinois_Rockford":{"name":"Rockford"},"US_Illinois_Springfield":{"name":"Springfield"},"US_Illinois_Waukegan":{"name":"Waukegan"}}},"US_Indiana":{"name":"Indiana","abbr":"IN","regions":{"US_Indiana_Evansville":{"name":"Evansville"},"US_Indiana_Fort Wayne":{"name":"Fort Wayne"},"US_Indiana_Indianapolis":{"name":"Indianapolis"}}},"US_Iowa":{"name":"Iowa","abbr":"IA","regions":{"US_Iowa_Cedar Rapids":{"name":"Cedar Rapids"},"US_Iowa_Davenport":{"name":"Davenport"},"US_Iowa_Des Moines":{"name":"Des Moines"}}},"US_Kansas":{"name":"Kansas","abbr":"KS","regions":{"US_Kansas_Abilene":{"name":"Abilene"},"US_Kansas_Hutchinson":{"name":"Hutchinson"},"US_Kansas_Kansas City":{"name":"Kansas City"},"US_Kansas_Lawrence":{"name":"Lawrence"},"US_Kansas_Leavenworth":{"name":"Leavenworth"},"US_Kansas_Manhattan":{"name":"Manhattan"},"US_Kansas_Overland Park":{"name":"Overland Park"},"US_Kansas_Topeka":{"name":"Topeka"},"US_Kansas_Wichita":{"name":"Wichita"}}},"US_Kentucky":{"name":"Kentucky","abbr":"KY","regions":{"US_Kentucky_Lexington":{"name":"Lexington"},"US_Kentucky_Louisville":{"name":"Louisville"},"US_Kentucky_Owensboro":{"name":"Owensboro"}}},"US_Louisiana":{"name":"Louisiana","abbr":"LA","regions":{"US_Louisiana_Baton Rouge":{"name":"Baton Rouge"},"US_Louisiana_New Orleans":{"name":"New Orleans"},"US_Louisiana_Shreveport":{"name":"Shreveport"}}},"US_Maine":{"name":"Maine","abbr":"ME","regions":{"US_Maine_Bangor":{"name":"Bangor"},"US_Maine_Lewiston":{"name":"Lewiston"},"US_Maine_Portland":{"name":"Portland"}}},"US_Maryland":{"name":"Maryland","abbr":"MD","regions":{"US_Maryland_Balitmore":{"name":"Balitmore"},"US_Maryland_Gaithersburg":{"name":"Gaithersburg"},"US_Maryland_Rockville":{"name":"Rockville"}}},"US_Massachusetts":{"name":"Massachusetts","abbr":"MA","regions":{"US_Massachusetts_Boston":{"name":"Boston"},"US_Massachusetts_Springfield":{"name":"Springfield"},"US_Massachusetts_Worcester":{"name":"Worcester"}}},"US_Michigan":{"name":"Michigan","abbr":"MI","regions":{"US_Michigan_Ann Arbor":{"name":"Ann Arbor"},"US_Michigan_Battle Creek":{"name":"Battle Creek"},"US_Michigan_Bay City":{"name":"Bay City"},"US_Michigan_Dearborn":{"name":"Dearborn"},"US_Michigan_Detroit":{"name":"Detroit"},"US_Michigan_Flint":{"name":"Flint"},"US_Michigan_Grand Rapids":{"name":"Grand Rapids"},"US_Michigan_Kalamazoo":{"name":"Kalamazoo"},"US_Michigan_Lansing":{"name":"Lansing"},"US_Michigan_Muskegon":{"name":"Muskegon"},"US_Michigan_Pontiac":{"name":"Pontiac"},"US_Michigan_Port Huron":{"name":"Port Huron"},"US_Michigan_Saginaw":{"name":"Saginaw"},"US_Michigan_Sault Ste Marie":{"name":"Sault Ste Marie"},"US_Michigan_Warren":{"name":"Warren"},"US_Michigan_Wyandotte":{"name":"Wyandotte"}}},"US_Minnesota":{"name":"Minnesota","abbr":"MN","regions":{"US_Minnesota_Minneapolis":{"name":"Minneapolis"},"US_Minnesota_Rochester":{"name":"Rochester"},"US_Minnesota_Saint Paul":{"name":"Saint Paul"}}},"US_Mississippi":{"name":"Mississippi","abbr":"MS","regions":{"US_Mississippi_Biloxi":{"name":"Biloxi"},"US_Mississippi_Greenville":{"name":"Greenville"},"US_Mississippi_Gulfport":{"name":"Gulfport"},"US_Mississippi_Hattiesburg":{"name":"Hattiesburg"},"US_Mississippi_Jackson":{"name":"Jackson"},"US_Mississippi_Meridian":{"name":"Meridian"},"US_Mississippi_Vicksburg":{"name":"Vicksburg"}}},"US_Missouri":{"name":"Missouri","abbr":"MO","regions":{"US_Missouri_Columbia":{"name":"Columbia"},"US_Missouri_Jefferson City":{"name":"Jefferson City"},"US_Missouri_Kansas City":{"name":"Kansas City"},"US_Missouri_Saint Louis":{"name":"Saint Louis"},"US_Missouri_Springfield":{"name":"Springfield"}}},"US_Montana":{"name":"Montana","abbr":"MT","regions":{"US_Montana_Billings":{"name":"Billings"},"US_Montana_Great Falls":{"name":"Great Falls"},"US_Montana_Missoula":{"name":"Missoula"}}},"US_Nebraska":{"name":"Nebraska","abbr":"NE","regions":{"US_Nebraska_Bellevue":{"name":"Bellevue"},"US_Nebraska_Lincoln":{"name":"Lincoln"},"US_Nebraska_Omaha":{"name":"Omaha"}}},"US_Nevada":{"name":"Nevada","abbr":"NV","regions":{"US_Nevada_Carson City":{"name":"Carson City"},"US_Nevada_Elko":{"name":"Elko"},"US_Nevada_Henderson":{"name":"Henderson"},"US_Nevada_Las Vegas":{"name":"Las Vegas"},"US_Nevada_North Las Vegas":{"name":"North Las Vegas"},"US_Nevada_Reno":{"name":"Reno"},"US_Nevada_Sparks":{"name":"Sparks"},"US_Nevada_Virginia City":{"name":"Virginia City"}}},"US_New Hampshire":{"name":"New Hampshire","abbr":"NH","regions":{"US_New Hampshire_Concord":{"name":"Concord"},"US_New Hampshire_Manchester":{"name":"Manchester"},"US_New Hampshire_Nashua":{"name":"Nashua"}}},"US_New Jersey":{"name":"New Jersey","abbr":"NJ","regions":{"US_New Jersey_Jersey City":{"name":"Jersey City"},"US_New Jersey_Newark":{"name":"Newark"},"US_New Jersey_Paterson":{"name":"Paterson"}}},"US_New Mexico":{"name":"New Mexico","abbr":"NM","regions":{"US_New Mexico_Albuquerque":{"name":"Albuquerque"},"US_New Mexico_Las Cruces":{"name":"Las Cruces"},"US_New Mexico_Roswell":{"name":"Roswell"},"US_New Mexico_Santa Fe":{"name":"Santa Fe"}}},"US_New York":{"name":"New York","abbr":"NY","regions":{"US_New York_Buffalo":{"name":"Buffalo"},"US_New York_New York":{"name":"New York"},"US_New York_Rochester":{"name":"Rochester"}}},"US_North Carolina":{"name":"North Carolina","abbr":"NC","regions":{"US_North Carolina_Asheville":{"name":"Asheville"},"US_North Carolina_Chapel Hill":{"name":"Chapel Hill"},"US_North Carolina_Charlotte":{"name":"Charlotte"},"US_North Carolina_Durham":{"name":"Durham"},"US_North Carolina_Greensboro":{"name":"Greensboro"},"US_North Carolina_Raleigh":{"name":"Raleigh"},"US_North Carolina_Raleigh-Durham":{"name":"Raleigh-Durham"}}},"US_North Dakota":{"name":"North Dakota","abbr":"ND","regions":{"US_North Dakota_Bismarck":{"name":"Bismarck"},"US_North Dakota_Fargo":{"name":"Fargo"},"US_North Dakota_Grand Forks":{"name":"Grand Forks"},"US_North Dakota_Minot":{"name":"Minot"}}},"US_Ohio":{"name":"Ohio","abbr":"OH","regions":{"US_Ohio_Cincinnati":{"name":"Cincinnati"},"US_Ohio_Cleveland":{"name":"Cleveland"},"US_Ohio_Columbus":{"name":"Columbus"},"US_Ohio_Dayton":{"name":"Dayton"},"US_Ohio_Toledo":{"name":"Toledo"}}},"US_Oklahoma":{"name":"Oklahoma","abbr":"OK","regions":{"US_Oklahoma_Norman":{"name":"Norman"},"US_Oklahoma_Oklahoma City":{"name":"Oklahoma City"},"US_Oklahoma_Tulsa":{"name":"Tulsa"}}},"US_Oregon":{"name":"Oregon","abbr":"OR","regions":{"US_Oregon_Bend":{"name":"Bend"},"US_Oregon_Coos Bay":{"name":"Coos Bay"},"US_Oregon_Corvallis":{"name":"Corvallis"},"US_Oregon_Crater Lake":{"name":"Crater Lake"},"US_Oregon_Dallas":{"name":"Dallas"},"US_Oregon_Eugene":{"name":"Eugene"},"US_Oregon_Grant's Pass":{"name":"Grant's Pass"},"US_Oregon_Hood River":{"name":"Hood River"},"US_Oregon_Medford":{"name":"Medford"},"US_Oregon_Portland":{"name":"Portland"},"US_Oregon_Salem":{"name":"Salem"},"US_Oregon_Springfield":{"name":"Springfield"},"US_Oregon_St Helens":{"name":"St Helens"},"US_Oregon_The Dalles":{"name":"The Dalles"},"US_Oregon_Tillamook":{"name":"Tillamook"}}},"US_Pennsylvania":{"name":"Pennsylvania","abbr":"PA","regions":{"US_Pennsylvania_Allentown":{"name":"Allentown"},"US_Pennsylvania_Philadephia":{"name":"Philadephia"},"US_Pennsylvania_Pittsburgh":{"name":"Pittsburgh"}}},"US_Rhode Island":{"name":"Rhode Island","abbr":"RI","regions":{"US_Rhode Island_Cranston":{"name":"Cranston"},"US_Rhode Island_Newport":{"name":"Newport"},"US_Rhode Island_Pawtucket":{"name":"Pawtucket"},"US_Rhode Island_Providence":{"name":"Providence"},"US_Rhode Island_Warwick":{"name":"Warwick"},"US_Rhode Island_Westerly":{"name":"Westerly"},"US_Rhode Island_Woonsocket":{"name":"Woonsocket"}}},"US_South Carolina":{"name":"South Carolina","abbr":"SC","regions":{"US_South Carolina_Charleston":{"name":"Charleston"},"US_South Carolina_Columbia":{"name":"Columbia"},"US_South Carolina_North Charleston":{"name":"North Charleston"}}},"US_South Dakota":{"name":"South Dakota","abbr":"SD","regions":{"US_South Dakota_Aberdeen":{"name":"Aberdeen"},"US_South Dakota_Rapid City":{"name":"Rapid City"},"US_South Dakota_Sioux Falls":{"name":"Sioux Falls"}}},"US_Tennessee":{"name":"Tennessee","abbr":"TN","regions":{"US_Tennessee_Bristol":{"name":"Bristol"},"US_Tennessee_Chattanooga":{"name":"Chattanooga"},"US_Tennessee_Johnson City":{"name":"Johnson City"},"US_Tennessee_Kingsport":{"name":"Kingsport"},"US_Tennessee_Knoxville":{"name":"Knoxville"},"US_Tennessee_Memphis":{"name":"Memphis"},"US_Tennessee_Nashville":{"name":"Nashville"},"US_Tennessee_Smyrna":{"name":"Smyrna"},"US_Tennessee_Spring Hill":{"name":"Spring Hill"},"US_Tennessee_Tri-City Area":{"name":"Tri-City Area"}}},"US_Texas":{"name":"Texas","abbr":"TX","regions":{"US_Texas_Austin":{"name":"Austin"},"US_Texas_Corpus Christi":{"name":"Corpus Christi"},"US_Texas_Dallas":{"name":"Dallas"},"US_Texas_El Paso":{"name":"El Paso"},"US_Texas_Galveston":{"name":"Galveston"},"US_Texas_Houston":{"name":"Houston"},"US_Texas_Laredo":{"name":"Laredo"},"US_Texas_Mcallen":{"name":"McAllen"},"US_Texas_San Antonio":{"name":"San Antonio"}}},"US_Utah":{"name":"Utah","abbr":"UT","regions":{"US_Utah_Layton":{"name":"Layton"},"US_Utah_Ogden":{"name":"Ogden"},"US_Utah_Orem":{"name":"Orem"},"US_Utah_Park City":{"name":"Park City"},"US_Utah_Provo":{"name":"Provo"},"US_Utah_Salt Lake City":{"name":"Salt Lake City"},"US_Utah_St.George":{"name":"St.George"},"US_Utah_West Valley City":{"name":"West Valley City"}}},"US_Vermont":{"name":"Vermont","abbr":"VT","regions":{"US_Vermont_Burlington":{"name":"Burlington"},"US_Vermont_Rutland":{"name":"Rutland"},"US_Vermont_South Burlington":{"name":"South Burlington"}}},"US_Virginia":{"name":"Virginia","abbr":"VA","regions":{"US_Virginia_Chesapeake":{"name":"Chesapeake"},"US_Virginia_Norfolk":{"name":"Norfolk"},"US_Virginia_Virginia Beach":{"name":"Virginia Beach"}}},"US_Washington":{"name":"Washington","abbr":"WA","regions":{"US_Washington_Seattle":{"name":"Seattle"},"US_Washington_Spokane":{"name":"Spokane"},"US_Washington_Tacoma":{"name":"Tacoma"}}},"US_West Virginia":{"name":"West Virginia","abbr":"WV","regions":{"US_West Virginia_Charleston":{"name":"Charleston"},"US_West Virginia_Huntington":{"name":"Huntington"},"US_West Virginia_Parkersburg":{"name":"Parkersburg"}}},"US_Wisconsin":{"name":"Wisconsin","abbr":"WI","regions":{"US_Wisconsin_Appleton":{"name":"Appleton"},"US_Wisconsin_Eau Claire":{"name":"Eau Claire"},"US_Wisconsin_Green Bay":{"name":"Green Bay"},"US_Wisconsin_Kenosha":{"name":"Kenosha"},"US_Wisconsin_Lacrosse":{"name":"LaCrosse"},"US_Wisconsin_Madison":{"name":"Madison"},"US_Wisconsin_Manitowoc":{"name":"Manitowoc"},"US_Wisconsin_Milwaukee":{"name":"Milwaukee"},"US_Wisconsin_Oshkosh":{"name":"Oshkosh"},"US_Wisconsin_Racine":{"name":"Racine"},"US_Wisconsin_Sheboygan":{"name":"Sheboygan"},"US_Wisconsin_Wausau":{"name":"Wausau"}}},"US_Wyoming":{"name":"Wyoming","abbr":"WY","regions":{"US_Wyoming_Casper":{"name":"Casper"},"US_Wyoming_Cheyenne":{"name":"Cheyenne"},"US_Wyoming_Evanston":{"name":"Evanston"},"US_Wyoming_Laramie":{"name":"Laramie"},"US_Wyoming_Rock Springs":{"name":"Rock Springs"},"US_Wyoming_Sheridan":{"name":"Sheridan"}}}}},"CA":{"name":"Canada","regions":{"CA_Abbotsford":{"name":"Abbotsford"},"CA_Barrie":{"name":"Barrie"},"CA_Brampton":{"name":"Brampton"},"CA_Calgary":{"name":"Calgary"},"CA_Cape Breton":{"name":"Cape Breton"},"CA_Charlottetown":{"name":"Charlottetown"},"CA_Edmonton":{"name":"Edmonton"},"CA_Fredericton":{"name":"Fredericton"},"CA_Guelph":{"name":"Guelph"},"CA_Halifax":{"name":"Halifax"},"CA_Hamilton":{"name":"Hamilton"},"CA_Iqaluit":{"name":"Iqaluit"},"CA_Kelowna":{"name":"Kelowna"},"CA_Kingston":{"name":"Kingston"},"CA_London":{"name":"London"},"CA_Montreal":{"name":"Montreal"},"CA_Oshawa":{"name":"Oshawa"},"CA_Ottawa":{"name":"Ottawa"},"CA_Quebec":{"name":"Quebec"},"CA_Regina":{"name":"Regina"},"CA_Saint-John's":{"name":"Saint-John's"},"CA_Saskatoon":{"name":"Saskatoon"},"CA_Sherbrooke":{"name":"Sherbrooke"},"CA_St. Catharines":{"name":"St. Catharines"},"CA_Sudbury":{"name":"Sudbury"},"CA_Thunder Bay":{"name":"Thunder Bay"},"CA_Toronto":{"name":"Toronto"},"CA_Trois-Rivieres":{"name":"Trois-Rivieres"},"CA_Vancouver":{"name":"Vancouver"},"CA_Victoria":{"name":"Victoria"},"CA_Whitehorse":{"name":"Whitehorse"},"CA_Windsor":{"name":"Windsor"},"CA_Winnipeg":{"name":"Winnipeg"},"CA_Yellowknife":{"name":"Yellowknife"}}}}